generalization/__init__.py
generalization/version.py
generalization/models/__init__.py
generalization/models/factory.py
generalization/models/pytorch/__init__.py
generalization/models/pytorch/alexnet.py
generalization/models/pytorch/inception.py
generalization/models/pytorch/mlp.py
generalization/models/pytorch/resnet.py
generalization/randomization/__init__.py
generalization/randomization/builders.py
generalization/randomization/corruptions.py
generalization/randomization/dataset.py
generalization/randomization/transforms.py
generalization/randomization/utils.py
generalization/randomization/inputs/__init__.py
generalization/randomization/inputs/gaussian_pixels.py
generalization/randomization/inputs/random_pixels.py
generalization/randomization/inputs/shuffled_pixels.py
generalization/randomization/labels/__init__.py
generalization/randomization/labels/partial_labels.py
generalization/randomization/labels/random_labels.py
generalization/utils/__init__.py
generalization/utils/data.py
generalization/utils/experiment.py
generalization/utils/model.py
generalization/utils/scores.py
generalization/utils/train.py
generalization/utils/viz.py
ids_generalization-20240416.dist-info/LICENSE
ids_generalization-20240416.dist-info/METADATA
ids_generalization-20240416.dist-info/WHEEL
ids_generalization-20240416.dist-info/top_level.txt
ids_generalization-20240416.dist-info/RECORD
