Metadata-Version: 2.1
Name: ids-generalization
Version: 20240416
Summary: Experiment Suite for Understanding and Rethinking Generalization
Home-page: https://github.com/ids-uchile/Generalization
Author: Stepp1
License: BSD-3-Clause
Requires-Python: >=3.8
License-File: LICENSE
Requires-Dist: numpy
Requires-Dist: matplotlib
Provides-Extra: dev
Requires-Dist: pytest ; extra == 'dev'
Requires-Dist: black ; extra == 'dev'
Requires-Dist: flake8 ; extra == 'dev'
Requires-Dist: isort ; extra == 'dev'
